{
  "discord": {
    "token": "",
    "servers": [
      {
        "welcome": {
          "channel": 0,
          "title": "Welcome {user}",
          "description": "",
          "color": "E32C2C"
        },
        "guildId": 0,
        "statusChannel": 0,
        "streamingRole": 0,
        "pingedRole": 0,
        "streamers": [ "lofigirl" ]
      }
    ]
  },
  "youTube": {
    "apiKey": "",
    "clientId": ""
  },
  "twitch": {
    "clientId": "",
    "clientSecret": ""
  },
  "streamers": {
    "lofigirl": {
      "discordId": 0,
      "twitch": "lofigirl",
      "youtube": "@LofiGirl"
    }
  }
}